_paddlespeech_ctcdecoders.cp37-win_amd64.pyd
paddlespeech_ctcdecoders.py
paddlespeech_ldd_ctcdecoders-0.2.0.dist-info/COPYING.APACHE2.0
paddlespeech_ldd_ctcdecoders-0.2.0.dist-info/COPYING.LESSER.3
paddlespeech_ldd_ctcdecoders-0.2.0.dist-info/LICENSE
paddlespeech_ldd_ctcdecoders-0.2.0.dist-info/METADATA
paddlespeech_ldd_ctcdecoders-0.2.0.dist-info/WHEEL
paddlespeech_ldd_ctcdecoders-0.2.0.dist-info/top_level.txt
paddlespeech_ldd_ctcdecoders-0.2.0.dist-info/RECORD
